secsend/__init__.py
secsend/__version__.py
secsend/cli.py
secsend/client.py
secsend/crypto.py
secsend/metadata.py
secsend/stream.py
secsend/utils.py
secsend-1.1.1.data/scripts/secadmin
secsend-1.1.1.data/scripts/secdownload
secsend-1.1.1.data/scripts/secupload
secsend-1.1.1.dist-info/METADATA
secsend-1.1.1.dist-info/WHEEL
secsend-1.1.1.dist-info/top_level.txt
secsend-1.1.1.dist-info/RECORD
